{
  "ready_tokens": [
    {
      "email": "vitol80174@splindor.com",
      "device_id": "0fdf8ab8d48edc64",
      "token": "ZtTPopglyn6uYHes-50ArbL2UK2kJ88IjS8cTqufLeVjgCVEot0GgRDpnY7mmx9X",
      "created": "2026-05-25 02:43:44"
    },
    {
      "email": "tetajad626@virawolf.com",
      "device_id": "50b1b04ce3643fec",
      "token": "w9CX3Vim5JaXIv_whNneGm2HLs02Hj04W6-ASlSqhf9P5lQHK9y0OwaaqIRaEuNZ",
      "created": "2026-05-25 02:43:44"
    },
    {
      "email": "mesavo7548@wudmis.com",
      "device_id": "d1f48af03e8dd297",
      "token": "Fh_SQt_MjSrlwa3l7hfTdgEgbZxzPL8QGVC_QMeOdbWzOAqLzM-2hdgl9jwTfyZG",
      "created": "2026-05-25 02:43:44"
    },
    {
      "email": "mowene1419@wudmis.com",
      "device_id": "23fb9641b14b8695",
      "token": "EM7BvkV2ya3BQwCgRD4StDCSTzpgw8YMtWiBYaEhFTKWEhf6h7a8Q2WvwApNPpIw",
      "created": "2026-05-25 02:43:44"
    },
    {
      "email": "kipipa5543@toondot.com",
      "device_id": "132d3116597526f5",
      "token": "8_Bvc12ZCq81uuj-EmJiBMLepOnJnBAjjlvd-gsPwLkB8rCy0qmYHONVeC4y6ThZ",
      "created": "2026-05-25 02:43:44"
    },
    {
      "email": "vekagov392@virawolf.com",
      "device_id": "dbe1e53a1053b5ac",
      "token": "bwOtSKFSdssdvhPvAYeV-ox5V9kHmpUm7UeDuMeCnoac-9GTHDuo5sSyPlMrKOv_",
      "created": "2026-05-25 02:43:44"
    },
    {
      "email": "xiyev72116@viasuma.com",
      "device_id": "98ea8e1747c4866c",
      "token": "k6Fuu9QHvlgHsW145Z-EOemm0X361KPl93i1zoyA5p4hZzQrrGwcnnMf_Lk2Ofse",
      "created": "2026-05-25 02:43:44"
    },
    {
      "email": "vofif66427@toondot.com",
      "device_id": "d92db55072e98019",
      "token": "t8SkR1NzWBvpTfE6ZdPHUFIRxj7BL2zqRxMvgrBkhpUkqR8kcOQJsdzSMr1PFfky",
      "created": "2026-05-25 02:43:44"
    },
    {
      "email": "socobo9939@toondot.com",
      "device_id": "17fd629d3706db8d",
      "token": "q8T4GDEkpXrtbXAX7wfYSSGW-foLK4LUOSb4ovUfQhoJRR7hKCPx5I9f6Y2ec0hj",
      "created": "2026-05-25 02:43:44"
    },
    {
      "email": "sonivon559@toondot.com",
      "device_id": "5f45167eab40a31e",
      "token": "OHpNsBMvjArljT-5rjDFUCznSNWFqvKCGVpuIP-OC3RUmDxfjESfvjytp2OFU2Iy",
      "created": "2026-05-25 02:43:44"
    },
    {
      "email": "bijata1349@virawolf.com",
      "device_id": "3a4db7cd80cc61d3",
      "token": "jy3RQBi78iAXRreQPKlFlBMmt-cO_nuE3ZwxaoUFfbpmnpB4A6DgfcjDUSNH4kOf",
      "created": "2026-05-25 02:43:44"
    },
    {
      "email": "soxocet921@virawolf.com",
      "device_id": "112bc6dea7297076",
      "token": "QCNY5jvo8h_IeAdSSHlcSLw8F2STQnVIhwtmgRhxbbliibUcnKjlk9eg4GeXVpQC",
      "created": "2026-05-25 02:43:44"
    },
    {
      "email": "bohabi6421@toondot.com",
      "device_id": "31e0207d0666d113",
      "token": "MemOhQ9U1YgpWsv-gZ0IkE9lXVnUxuWUxel97ccnDntxNoge2oQA3mtiFXGcuDdh",
      "created": "2026-05-25 02:43:44"
    },
    {
      "email": "vekare9841@toondot.com",
      "device_id": "0195b85c4d71e8fe",
      "token": "soe4jFPlNXUPddsGu2zJUigJthMa1-3d3DNblwBMezm7QcvXaZHKIJwC8hiyicxR",
      "created": "2026-05-25 02:43:44"
    },
    {
      "email": "gecoce3700@virawolf.com",
      "device_id": "0b872ac2bb05168e",
      "token": "8pl0OIYyygh5XexHVqWlnfC5ZOPsD74ZLsgRj38dUj3iug-3_r1wSc9MZqRZhaP7",
      "created": "2026-05-25 02:43:44"
    },
    {
      "email": "yixoh77884@virawolf.com",
      "device_id": "3754b1688a65311e",
      "token": "GMXX59NIB7RP7S3qM238de6n-W8LmpPDQxVU136CYExYB3eBzOMFnySnoLV7kAzQ",
      "created": "2026-05-25 02:43:44"
    },
    {
      "email": "yogoda8710@virawolf.com",
      "device_id": "ee27ceb8004c9880",
      "token": "rtcNHEQRjbcdzZTVadgx6B6HO2zchpHJfZPobrs_im8hFLeeSaFYvGC-t86k3UgR",
      "created": "2026-05-25 02:43:44"
    },
    {
      "email": "nevapi7420@wudmis.com",
      "device_id": "fac780696e8aa698",
      "token": "4Zb3ukHPPUgIegEeugMfU7WAyF9qCYdCGp7X2MhC_mq1GCsl9ocJyr5_2uKr_iJt",
      "created": "2026-05-25 02:43:44"
    },
    {
      "email": "cewoy46257@virawolf.com",
      "device_id": "232bda875c07dbd3",
      "token": "BK54DyMAVxu1ueInxCOVDH8j_kCynF_0wOjV26Ui8xSYA96lb_f2HJOSfn6MVHrq",
      "created": "2026-05-25 02:43:44"
    },
    {
      "email": "mawohi5130@wudmis.com",
      "device_id": "95457882c2bde05c",
      "token": "3TPokxfm09LnAR-nSP9lRl2uOkTKwOh1-6wXoLY-YLL8iNlMRLigqAju69zOIHFa",
      "created": "2026-05-25 02:43:44"
    },
    {
      "email": "vamena5041@wudmis.com",
      "device_id": "72f523de13eb5d8d",
      "token": "DTTVHbMbscUKV8ZLnSOng7xctzEGh1qxKnXP3nMmxhjfouQxcQWaI8g6u12lHMft",
      "created": "2026-05-25 02:43:44"
    },
    {
      "email": "biveyo9606@tivogo.com",
      "device_id": "602abf75f9ebcf12",
      "token": "ZSnZ5ZiS-Hh78pb7shOKhAxC-ujvLXSUqQGSIWmPuLPXI-lR7KIOst8OJRZ1HF4l",
      "created": "2026-05-25 02:43:44"
    },
    {
      "email": "kelixih490@toondot.com",
      "device_id": "44de3167611891ea",
      "token": "xBemVBVsI2NcqULAoCLYpuuqJ_MOqyUr4vzotkMISpCWex3yjmYuLSla0OQ_L_rj",
      "created": "2026-05-25 02:43:44"
    },
    {
      "email": "joyace6881@splindor.com",
      "device_id": "3614b117b6d9bdee",
      "token": "hluCf_MbcobtW3yofv0jgXQWoEV7p5GMl2Gq6doUhzk6v8muGqGZ9It-BrKN2v8w",
      "created": "2026-05-25 02:43:44"
    },
    {
      "email": "tamoha1694@virawolf.com",
      "device_id": "c369006cd76b206e",
      "token": "PCt4tqZzRZpxuS7wtB5fKwxPqOpH6g9oK09cQ-z-_T2UH8hGlwGX3MKtd0pd6fV7",
      "created": "2026-05-25 02:43:44"
    },
    {
      "email": "cepohe6430@virawolf.com",
      "device_id": "81ffa97c6d829bc5",
      "token": "5ZEwaVanYyGAWWfsj7i9P4AdFPlyOBGiat8jOR6jQExyq76bFfw8rmc4F1HEtHF3",
      "created": "2026-05-25 02:43:44"
    },
    {
      "email": "nabila8078@splindor.com",
      "device_id": "025a896b0ac7e15b",
      "token": "NcWogfMpiJnHL2SyJhojUJswPdOmWf3_zL9voQMZOiAZuNnRSUU83m6kjCUGheqw",
      "created": "2026-05-25 02:43:44"
    },
    {
      "email": "jawovir429@toondot.com",
      "device_id": "a28ba6968e5d8d07",
      "token": "pifC-WYbRVaH7iMzvkYhRtvGPnIIpTpUta2vwqamkhvQeGBdq6u5pur9CTCfa5Zb",
      "created": "2026-05-25 02:43:44"
    },
    {
      "email": "bovobaf404@splindor.com",
      "device_id": "a65ecc4875b853b3",
      "token": "xsmQwgkTl6-s25yS5_OgqHYQtXSnyNIHsp3-uyOF2JXa1ZhhC8L8EwhM7ztHs40j",
      "created": "2026-05-25 02:43:44"
    },
    {
      "email": "dageh63242@splindor.com",
      "device_id": "7019923fe8b3952e",
      "token": "0uJtVQ_om1aK8OBdM7vPb9Fn2WqqSP1r3ZqelWOj34m2cCWxA7CgFiaBKTvbZup6",
      "created": "2026-05-25 02:43:44"
    },
    {
      "email": "yonin47971@wudmis.com",
      "device_id": "da19b71bc87dacd9",
      "token": "4G_LhKmed4FilNnfH-rxju0BKcC_h0SO0j4QDFFW8vLmnqqeZjlDAgw-x_pQEiw8",
      "created": "2026-05-25 02:43:44"
    },
    {
      "email": "tayiwem842@wudmis.com",
      "device_id": "bc5861a550945f7d",
      "token": "q6F72ImofHZi61aHxThyRAZaUoJuMO8OFzPj1oYtgVvGmm50KoQeVNw85UEBtChy",
      "created": "2026-05-25 02:43:44"
    },
    {
      "email": "nowejew669@viasuma.com",
      "device_id": "ed11afd77e3df91c",
      "token": "3uEuqhJPxTwhgeSWCe2AQLJGn44STfWeGYEwsZAUyDe0crvLWNvx_nQ2xoYxT599",
      "created": "2026-05-25 02:43:44"
    },
    {
      "email": "semeti2256@wudmis.com",
      "device_id": "83eddfad49f74a1e",
      "token": "LkLfU2K6tzqLEAwKRwBdHEFu1nhAgqLPuEZB_QMsn3OUMMoxbFtpFF2bYKuEZl92",
      "created": "2026-05-25 02:43:44"
    },
    {
      "email": "ribope4585@splindor.com",
      "device_id": "99b6f8abf823df96",
      "token": "mNBzhP6xz03-oMq4L1VB9gFjK12f_BhqNgKkn5MEYl-EMuglaKDxbWOr9ROONjs3",
      "created": "2026-05-25 02:43:44"
    },
    {
      "email": "penedi6909@tivogo.com",
      "device_id": "ea79162d7a2d525e",
      "token": "a3EcYntDr_wsS8x4dWz2kRO56_aHaYxsoRegcY4zzJewTLa3RPse9xGRs4eMFvO6",
      "created": "2026-05-25 02:43:44"
    },
    {
      "email": "bivotav804@splindor.com",
      "device_id": "21e6ac1bb73237e6",
      "token": "pzrByajDMyi_kdJgu8tHVTJSxJpx6uPI_oH-0fRWM63vLRLV8u09ql3fdfNLoAag",
      "created": "2026-05-25 02:43:44"
    },
    {
      "email": "rakehit570@splindor.com",
      "device_id": "9f4d2c370b5256d8",
      "token": "uvYBAaexoYgorgchuwfs2JIzll51Wp3rzUBasNn9i-J60r58uCp3tK8qh8JIEWT_",
      "created": "2026-05-25 02:43:44"
    },
    {
      "email": "kamil26539@tivogo.com",
      "device_id": "0c9d240cc9cd7d7f",
      "token": "387msre5cmCasH0Pa2u1AR3lo3SWD7BBhL6m8CTTt6gY9p9kynNfyj6LcIQnDwDj",
      "created": "2026-05-25 02:43:44"
    },
    {
      "email": "bavakej461@splindor.com",
      "device_id": "d9eb06afb3cf4c3f",
      "token": "G-zngS9A0gleoZmTaVKLROHSz-OgUu7a54nEnkTZlJbARPhLEQeOT3PTtZPTUuvz",
      "created": "2026-05-25 02:43:44"
    },
    {
      "email": "xokiwoc799@toondot.com",
      "device_id": "b2a6e6eaef55eeb1",
      "token": "nTjsNX4xRZhUI9YW9XK4zCzwh_CIQZAno_cQg7YVW_0Uef_wq-xvCqB_yJZ7iBRR",
      "created": "2026-05-25 02:43:44"
    },
    {
      "email": "sapotif220@viasuma.com",
      "device_id": "828d9fa51a342d40",
      "token": "S-u333_6FvrdKOcT590zSe67Qp_qYS88ZTSr3j8T_mU1ckbyRg1h8LrjYeWNY0gT",
      "created": "2026-05-25 02:43:44"
    },
    {
      "email": "cirisa4115@toondot.com",
      "device_id": "0d813a9923c14482",
      "token": "RFCM2n6lPy1b3fDMCwYKpaJM626q8UyJCgZrADTIMPFPGSp6-IjKOlng6ttXm2et",
      "created": "2026-05-25 02:43:44"
    },
    {
      "email": "porayid231@tivogo.com",
      "device_id": "a1c6b801743e780a",
      "token": "lWcrvLSX0qtqhgvKYV26V5gLR8VFfO9IZrcYm8nVyCvG00AylYO1FwbSoSmpfuXS",
      "created": "2026-05-25 02:43:44"
    },
    {
      "email": "hopav28949@wudmis.com",
      "device_id": "8c877b766a8b8102",
      "token": "q6mDAp8c5CANag9cNEkbkkrOVqO0H7-45S6kViYR_prITyRTtOuEW4C9LozsAsaB",
      "created": "2026-05-25 02:43:44"
    },
    {
      "email": "gameri6409@splindor.com",
      "device_id": "2f26617f83ee41e4",
      "token": "PoykU7SddxeD__MyE4qclECyUQyi06SPwuG-Eg23b8ZmEP-VvibsDvj8gfYtCVvy",
      "created": "2026-05-25 02:43:44"
    },
    {
      "email": "foleri8243@virawolf.com",
      "device_id": "aa19e4aed0ef2861",
      "token": "k1kPNqou20Jt3aph_rYLKy9hyyaN63D3zFNVWRl2pvfQF61Ak2JkRvQZLuBKKp3l",
      "created": "2026-05-25 02:43:44"
    },
    {
      "email": "legata5336@virawolf.com",
      "device_id": "499ba3acde53b0f3",
      "token": "bbum7L-tYhat6--f0PZQo0mRvT58Bb6S2oeq-xexKwZH7rSMXSU7YWYhgNplKwEr",
      "created": "2026-05-25 02:43:44"
    },
    {
      "email": "xerel96432@tivogo.com",
      "device_id": "746502ff7985b90d",
      "token": "lAoaas7GPCG8M6rOxUFPypYk_OR3mYqhiRvqPrpSqDLuDmWJOl-zjzgDuZaQZPcN",
      "created": "2026-05-25 02:43:44"
    },
    {
      "email": "dajimix173@toondot.com",
      "device_id": "a8e9f47080a6c20e",
      "token": "or-KJD1pupFmWdapbHU5PqY7U7PVeSsByVPhIAsssoNfE8lCiuluJRt4Mnic1a6u",
      "created": "2026-05-25 02:43:44"
    },
    {
      "email": "fokiro6728@toondot.com",
      "device_id": "b1f41ae8a366a045",
      "token": "tNlsMdygY3b4pK5-agDMJmXKJhdnYUvF3M_VjnDW2BcPa0qbCV6XlkXzA7gVNbmR",
      "created": "2026-05-25 02:43:44"
    },
    {
      "email": "kajey39289@splindor.com",
      "device_id": "faa48d88b0e85834",
      "token": "XVq1vBVTvh1g_JFWYdNLnWsL4I9hzUeX-nINHh0LAqV0RQO_9MjGR2PJopw9rTim",
      "created": "2026-05-25 02:43:44"
    },
    {
      "email": "nehefa6365@viasuma.com",
      "device_id": "cc0a0259a111c4a7",
      "token": "2K0HiPkNvv81zZz4aXICRss8VMcrxxk593VcrHle1NeSQ5fkXaPvXWjKzFooOyjE",
      "created": "2026-05-25 02:43:44"
    },
    {
      "email": "povejog969@toondot.com",
      "device_id": "33750b6bc67e9537",
      "token": "YSQDD9kcjdOZWozJv4aOvKMNLkIPgCxZbxY85yk2WQtmY94z-IUdcRLjx5mf9vD6",
      "created": "2026-05-25 02:43:44"
    },
    {
      "email": "wisis29698@toondot.com",
      "device_id": "550249e8e0ecc4c3",
      "token": "QrmaGJwho1oJGH1JWydi0SkKyGlDxS-fbZTd7uA4BGo5WDuA-4n1PZWnZONEI0mp",
      "created": "2026-05-25 02:43:44"
    },
    {
      "email": "pamoyax481@toondot.com",
      "device_id": "7784ee6f4d8abd0a",
      "token": "yQ_nYZVqwGWaaAkM1YNhOTB_5K09qlZxF27XJVszbv8bPwCD9a7FfrbO66KQd1eD",
      "created": "2026-05-25 02:43:44"
    },
    {
      "email": "banaki2896@splindor.com",
      "device_id": "bd832416418731e8",
      "token": "eHRgL0yufIcIhZ6IzeQbG7JPTTNzwd-f_3lj1Uc3B804tgfWQye-U1tTDSVEyX-C",
      "created": "2026-05-25 02:43:44"
    },
    {
      "email": "yelom22991@tivogo.com",
      "device_id": "b5b72554f9c5ea26",
      "token": "RXk_qgEdyVzwJP3XNlJYKfArgnJvdmolPZJqBCMXv1OuLAczhRNUAPmr-ikS2l1d",
      "created": "2026-05-25 02:43:44"
    },
    {
      "email": "bojor59479@tivogo.com",
      "device_id": "b00c1c67fa903026",
      "token": "ThwH3NrErJhRaxh1jY8HKUUrYS4CvHzQrtWCPyr-LYIn6cm1ugTMXKaraDTqJMaJ",
      "created": "2026-05-25 02:43:44"
    },
    {
      "email": "kolilop722@tivogo.com",
      "device_id": "849584e8940d3b22",
      "token": "VGfwoXX6ozG7WNWCsi1-qBf6ZguvLMteis5_WOquQ9n8Mq7I2DNHlDVB9VTNrSBi",
      "created": "2026-05-25 02:43:44"
    },
    {
      "email": "batip63194@splindor.com",
      "device_id": "923d2b15596e3560",
      "token": "eGMvvhJ39btzC2iJ82N6vT9jQmqgkAS8OCTy3Y79VKCjN-mkus3V0Sp5wxktR7tP",
      "created": "2026-05-25 02:43:44"
    },
    {
      "email": "pagiwiy855@splindor.com",
      "device_id": "ca8287e8aaf09329",
      "token": "xReL-0GWvlPaiAz6auHJPT6fzC6ozDCmhFupTKwFSR-RAkAzBlfrr-ppLX249Ijo",
      "created": "2026-05-25 02:43:44"
    },
    {
      "email": "gicapo4513@wudmis.com",
      "device_id": "3c0046d13368ec6c",
      "token": "08O-7JgcKMP_JO-doPWBrciOFWVAY8XJCaNYpjFJHxR2pLAUKiwOa0875zVOxxAl",
      "created": "2026-05-25 02:43:44"
    },
    {
      "email": "lonoje9868@splindor.com",
      "device_id": "8d2336fa8eca6aca",
      "token": "lj_ROU3ahTGq-86siuJY7KUwd24bezrP9WUCzdg42eRi2hTm7Aa81zV2n7IkA0qE",
      "created": "2026-05-25 02:43:44"
    },
    {
      "email": "wataj84159@tivogo.com",
      "device_id": "72fccbb16a8b8910",
      "token": "WZnH2ZUqxLmQUuPDi9uEUQDmVODUsKPVDlz7R07QjF2ySpaJA3g8Gbty6hagGryG",
      "created": "2026-05-25 02:43:44"
    },
    {
      "email": "menepoj151@splindor.com",
      "device_id": "18323b265aeb5f6c",
      "token": "2kN1N0lIBEEVPk22m0h9MX7bsPOA8r2Ow_f-TDiLD2pIjLM5FbUwDTOq3_bjZu1H",
      "created": "2026-05-25 02:43:44"
    },
    {
      "email": "fonenel841@wudmis.com",
      "device_id": "fc6f74170c574ed7",
      "token": "-pG65KsV0QZQ36IqpqzHj1lvRmNJPBraPKnEkK4CnaiLS4OHKsPXDkWFoHgcCqYX",
      "created": "2026-05-25 02:43:45"
    },
    {
      "email": "gorac22807@splindor.com",
      "device_id": "8636551a2b614478",
      "token": "xIcyMlhO7pBFvh6dtAaaWMmlwY0O9XI9Frfiu2jksPBvWxpksGP5WPzeVOhsO4ut",
      "created": "2026-05-25 02:43:45"
    },
    {
      "email": "bahaw19181@toondot.com",
      "device_id": "f1e98bbbc5945274",
      "token": "ROHuGY6trEU3QyGDqbo3Piq4fQlgJpY3G8KYH9k3KZSpSalqlT4WXvgPprt0EFJU",
      "created": "2026-05-25 02:43:45"
    },
    {
      "email": "lehiga4579@toondot.com",
      "device_id": "64190181b55b6e73",
      "token": "sXhwvwBE7gqno8Z0TAVwi_jkyfLhFQwtQzkEZdl2M9UeVF186lxzzWZkpsU7qY7w",
      "created": "2026-05-25 02:43:45"
    },
    {
      "email": "pohewe3553@toondot.com",
      "device_id": "c8d1a93ca02079f6",
      "token": "r_hP46YlJ8YiF1rD7rqQObrNIixq1nNkqri0kkN_e8zYu_DBxzckZJW7MVHl5tEI",
      "created": "2026-05-25 02:43:45"
    },
    {
      "email": "yikinac878@splindor.com",
      "device_id": "0ab5800078758b18",
      "token": "XUemixvsCs6-Dn2zoyF_d_rQAZBV-Xf4oScWFuXcVSBfiEnWybrLm9BVXtdW14B4",
      "created": "2026-05-25 02:43:45"
    },
    {
      "email": "cojem86579@toondot.com",
      "device_id": "95625f14cef8fdbe",
      "token": "CO5A7kZHeTJR5apT4trfH-ukUlv1OQPOmzb7vNRJhfXQv6s2_1lP7z0kHbnwMC-T",
      "created": "2026-05-25 02:43:45"
    },
    {
      "email": "higeyo5683@toondot.com",
      "device_id": "5aea9e1b0b2c1e00",
      "token": "SOJVZbntbsKwnTc94HaoaCerT86UL02F-mSByBFShH36t1os_O2dWuYRWL5iVb_3",
      "created": "2026-05-25 02:43:45"
    },
    {
      "email": "yimebim815@virawolf.com",
      "device_id": "9d581c71c8547e91",
      "token": "mBddTNm-QnhNINMT_3sJ_3evJdoKRDQxgWl4pvtSrRFYyNqlDpGX8-NIiiHJAsJh",
      "created": "2026-05-25 02:43:45"
    },
    {
      "email": "kofise8751@wudmis.com",
      "device_id": "342a313d7b51dc30",
      "token": "5e_j69TitylVq5Av1xfl2M9f2hgmoX96i6C35miUJZICJP61SccMzIk3ILBFOI6p",
      "created": "2026-05-25 02:43:45"
    },
    {
      